gawseed/__init__.py
gawseed/__init__.py.bak
gawseed/averageWindow.py
gawseed/algorithm/__init__.py
gawseed/algorithm/__init__.py.bak
gawseed/algorithm/aggregator.py
gawseed/algorithm/aggregator.py.bak
gawseed/algorithm/dns.py
gawseed/algorithm/dns.py.bak
gawseed/algorithm/filter.py
gawseed/algorithm/filter.py.bak
gawseed/algorithm/generic.py
gawseed/algorithm/generic.py.bak
gawseed/algorithm/generic_ext.py
gawseed/algorithm/generic_ext.py.bak
gawseed/algorithm/relationship.py
gawseed/algorithm/relationship.py.bak
gawseed/algorithm/tld.py
gawseed/algorithm/tld.py.bak
gawseed/analysis/__init__.py
gawseed/analysis/__init__.py.bak
gawseed/analysis/aggregator.py
gawseed/analysis/aggregator.py.bak
gawseed/analysis/edgeDetect.py
gawseed/analysis/edgeDetect.py.bak
gawseed/analysis/featureCounter.py
gawseed/analysis/featureCounter.py.bak
gawseed/analysis/relationshipAnalysis.py
gawseed/analysis/relationshipAnalysis.py.bak
gawseed/scripts/__init__.py
gawseed/scripts/__init__.py.bak
gawseed/scripts/aggregator.py
gawseed/scripts/aggregator.py.bak
gawseed/scripts/featureCounter.py
gawseed/scripts/featureCounter.py.bak
gawseed/scripts/relationshipAnalysis.py
gawseed/scripts/relationshipAnalysis.py.bak
gawseed/support/__init__.py
gawseed/support/__init__.py.bak
gawseed/support/functionLoader.py
gawseed/support/functionLoader.py.bak
gawseed_processing-0.9.1.dist-info/METADATA
gawseed_processing-0.9.1.dist-info/WHEEL
gawseed_processing-0.9.1.dist-info/entry_points.txt
gawseed_processing-0.9.1.dist-info/top_level.txt
gawseed_processing-0.9.1.dist-info/RECORD
