Metadata-Version: 2.1
Name: gawseed-processing
Version: 0.9.1
Summary: A data processing engine for statistically analyzing time series data
Home-page: https://github.com/gawseed/processing
Author: Wes Hardaker and USC/ISI
Author-email: opensource@hardakers.net
License: UNKNOWN
Platform: UNKNOWN
Classifier: Programming Language :: Python :: 3
Classifier: Operating System :: OS Independent
Requires-Python: >=3.0
